cyberfusion/NextCloudSupport/__init__.py
cyberfusion/NextCloudSupport/_occ.py
cyberfusion/NextCloudSupport/app.py
cyberfusion/NextCloudSupport/exceptions.py
cyberfusion/NextCloudSupport/instance.py
cyberfusion/NextCloudSupport/user.py
python3_cyberfusion_nextcloud_support-1.2.1.dist-info/METADATA
python3_cyberfusion_nextcloud_support-1.2.1.dist-info/WHEEL
python3_cyberfusion_nextcloud_support-1.2.1.dist-info/top_level.txt
python3_cyberfusion_nextcloud_support-1.2.1.dist-info/RECORD
