Metadata-Version: 2.4
Name: python3-cyberfusion-nextcloud-support
Version: 1.2.1
Summary: Library for NextCloud.
Author-email: Cyberfusion <support@cyberfusion.io>
Project-URL: Source, https://github.com/CyberfusionIO/python3-cyberfusion-nextcloud-support
Requires-Dist: python3-cyberfusion-common~=2.12
